{"v":"5.8.1","fr":60,"ip":0,"op":201,"w":412,"h":300,"nm":"Active_Edge_Squeeze_Silence","ddd":0,"assets":[],"layers":[{"ddd":0,"ind":1,"ty":4,"nm":".black","cl":"black","parent":2,"sr":1,"ks":{"o":{"a":1,"k":[{"i":{"x":[0.833],"y":[0.833]},"o":{"x":[0.167],"y":[0.167]},"t":35,"s":[0]},{"i":{"x":[0.833],"y":[0.833]},"o":{"x":[0.167],"y":[0.167]},"t":50,"s":[100]},{"i":{"x":[0.833],"y":[0.833]},"o":{"x":[0.167],"y":[0.167]},"t":152,"s":[100]},{"t":167,"s":[0]}],"ix":11},"r":{"a":0,"k":0,"ix":10},"p":{"a":0,"k":[206,207.055,0],"ix":2,"l":2},"a":{"a":0,"k":[206,207.055,0],"ix":1,"l":2},"s":{"a":0,"k":[100,100,100],"ix":6,"l":2}},"ao":0,"shapes":[{"ty":"gr","it":[{"ind":0,"ty":"sh","ix":1,"ks":{"a":0,"k":{"i":[[0.208,0],[1.417,0.665],[1.093,1.093],[0.665,1.417],[0,1.492],[-0.139,0.139],[-0.208,0],[0,0],[-0.127,-0.104],[-0.023,-0.162],[0,0],[0.029,-0.133],[0.104,-0.104],[0,0],[-0.729,-0.729],[-0.879,-0.532],[0,0],[-0.168,0.052],[-0.162,-0.023],[0,0],[-0.104,-0.121],[0,-0.162],[0,0],[0.139,-0.139]],"o":[[-1.492,0],[-1.417,-0.665],[-1.093,-1.093],[-0.665,-1.417],[0,-0.208],[0.139,-0.139],[0,0],[0.162,0],[0.127,0.104],[0,0],[0.023,0.162],[-0.029,0.133],[0,0],[0.486,0.833],[0.729,0.729],[0,0],[0.104,-0.104],[0.168,-0.052],[0,0],[0.162,0.035],[0.104,0.121],[0,0],[0,0.208],[-0.139,0.139]],"v":[[5.517,6.245],[1.154,5.248],[-2.611,2.611],[-5.248,-1.154],[-6.245,-5.517],[-6.037,-6.037],[-5.517,-6.245],[-2.706,-6.245],[-2.273,-6.089],[-2.047,-5.69],[-1.596,-3.261],[-1.605,-2.819],[-1.804,-2.463],[-3.47,-0.763],[-1.648,1.579],[0.763,3.47],[2.394,1.839],[2.802,1.605],[3.296,1.561],[5.69,2.047],[6.089,2.281],[6.245,2.706],[6.245,5.517],[6.037,6.037]],"c":true},"ix":2},"nm":"Path 5","mn":"ADBE Vector Shape - Group","hd":false},{"ty":"fl","c":{"a":0,"k":[0,0,0,1],"ix":4},"o":{"a":0,"k":100,"ix":5},"r":1,"bm":0,"nm":"Fill 1","mn":"ADBE Vector Graphic - Fill","hd":false},{"ty":"tr","p":{"a":0,"k":[206,207.055],"ix":2},"a":{"a":0,"k":[0,0],"ix":1},"s":{"a":0,"k":[100,100],"ix":3},"r":{"a":0,"k":0,"ix":6},"o":{"a":0,"k":100,"ix":7},"sk":{"a":0,"k":0,"ix":4},"sa":{"a":0,"k":0,"ix":5},"nm":"Transform"}],"nm":"Group 1","np":2,"cix":2,"bm":0,"ix":1,"mn":"ADBE Vector Group","hd":false}],"ip":0,"op":360,"st":0,"bm":0},{"ddd":0,"ind":2,"ty":4,"nm":".green400","cl":"green400","sr":1,"ks":{"o":{"a":1,"k":[{"i":{"x":[0.833],"y":[0.833]},"o":{"x":[0.167],"y":[0.167]},"t":35,"s":[0]},{"i":{"x":[0.833],"y":[0.833]},"o":{"x":[0.167],"y":[0.167]},"t":50,"s":[100]},{"i":{"x":[0.833],"y":[0.833]},"o":{"x":[0.167],"y":[0.167]},"t":152,"s":[100]},{"t":167,"s":[0]}],"ix":11},"r":{"a":0,"k":0,"ix":10},"p":{"a":1,"k":[{"i":{"x":0.1,"y":1},"o":{"x":0.167,"y":0.167},"t":35,"s":[206,229.055,0],"to":[0,-3.667,0],"ti":[0,3.667,0]},{"i":{"x":1,"y":1},"o":{"x":0.167,"y":0.167},"t":50,"s":[206,207.055,0],"to":[0,0,0],"ti":[0,0,0]},{"i":{"x":0.833,"y":0.833},"o":{"x":0.8,"y":0},"t":152,"s":[206,207.055,0],"to":[0,3.667,0],"ti":[0,-3.667,0]},{"t":167,"s":[206,229.055,0]}],"ix":2,"l":2},"a":{"a":0,"k":[206,207.055,0],"ix":1,"l":2},"s":{"a":0,"k":[100,100,100],"ix":6,"l":2}},"ao":0,"shapes":[{"ty":"gr","it":[{"ind":0,"ty":"sh","ix":1,"ks":{"a":0,"k":{"i":[[0,-7.652],[7.652,0],[0,7.652],[-7.652,0]],"o":[[0,7.652],[-7.652,0],[0,-7.652],[7.652,0]],"v":[[13.855,0],[0,13.855],[-13.855,0],[0,-13.855]],"c":true},"ix":2},"nm":"Path 1","mn":"ADBE Vector Shape - Group","hd":false},{"ty":"fl","c":{"a":0,"k":[0.35686275363,0.72549021244,0.454901963472,1],"ix":4},"o":{"a":0,"k":100,"ix":5},"r":1,"bm":0,"nm":"Fill 1","mn":"ADBE Vector Graphic - Fill","hd":false},{"ty":"tr","p":{"a":0,"k":[206,207.055],"ix":2},"a":{"a":0,"k":[0,0],"ix":1},"s":{"a":0,"k":[100,100],"ix":3},"r":{"a":0,"k":0,"ix":6},"o":{"a":0,"k":100,"ix":7},"sk":{"a":0,"k":0,"ix":4},"sa":{"a":0,"k":0,"ix":5},"nm":"Transform"}],"nm":"Group 2","np":2,"cix":2,"bm":0,"ix":1,"mn":"ADBE Vector Group","hd":false}],"ip":0,"op":360,"st":0,"bm":0},{"ddd":0,"ind":3,"ty":4,"nm":".green400","cl":"green400","parent":2,"sr":1,"ks":{"o":{"a":1,"k":[{"i":{"x":[0.833],"y":[0.833]},"o":{"x":[0.167],"y":[0.167]},"t":157,"s":[30]},{"t":167,"s":[0]}],"ix":11},"r":{"a":0,"k":0,"ix":10},"p":{"a":0,"k":[206,207.055,0],"ix":2,"l":2},"a":{"a":0,"k":[206,207.055,0],"ix":1,"l":2},"s":{"a":1,"k":[{"i":{"x":[0,0,0.667],"y":[1,1,1]},"o":{"x":[0.167,0.167,0.167],"y":[0.167,0.167,0]},"t":157,"s":[100,100,100]},{"t":189,"s":[155,155,100]}],"ix":6,"l":2}},"ao":0,"shapes":[{"ty":"gr","it":[{"ind":0,"ty":"sh","ix":1,"ks":{"a":0,"k":{"i":[[0,-7.652],[7.652,0],[0,7.652],[-7.652,0]],"o":[[0,7.652],[-7.652,0],[0,-7.652],[7.652,0]],"v":[[13.855,0],[0,13.855],[-13.855,0],[0,-13.855]],"c":true},"ix":2},"nm":"Path 1","mn":"ADBE Vector Shape - Group","hd":false},{"ty":"fl","c":{"a":0,"k":[0.35686275363,0.72549021244,0.454901963472,1],"ix":4},"o":{"a":0,"k":100,"ix":5},"r":1,"bm":0,"nm":"Fill 1","mn":"ADBE Vector Graphic - Fill","hd":false},{"ty":"tr","p":{"a":0,"k":[206,207.055],"ix":2},"a":{"a":0,"k":[0,0],"ix":1},"s":{"a":0,"k":[100,100],"ix":3},"r":{"a":0,"k":0,"ix":6},"o":{"a":0,"k":100,"ix":7},"sk":{"a":0,"k":0,"ix":4},"sa":{"a":0,"k":0,"ix":5},"nm":"Transform"}],"nm":"Group 2","np":2,"cix":2,"bm":0,"ix":1,"mn":"ADBE Vector Group","hd":false}],"ip":157,"op":189,"st":157,"bm":0},{"ddd":0,"ind":4,"ty":4,"nm":".green400","cl":"green400","sr":1,"ks":{"o":{"a":1,"k":[{"i":{"x":[0.833],"y":[0.833]},"o":{"x":[0.167],"y":[0.167]},"t":142,"s":[30]},{"t":152,"s":[0]}],"ix":11},"r":{"a":0,"k":0,"ix":10},"p":{"a":0,"k":[206,207.055,0],"ix":2,"l":2},"a":{"a":0,"k":[206,207.055,0],"ix":1,"l":2},"s":{"a":1,"k":[{"i":{"x":[0,0,0.667],"y":[1,1,1]},"o":{"x":[0.167,0.167,0.167],"y":[0.167,0.167,-1.905]},"t":120,"s":[100,100,100]},{"t":152,"s":[155,155,100]}],"ix":6,"l":2}},"ao":0,"shapes":[{"ty":"gr","it":[{"ind":0,"ty":"sh","ix":1,"ks":{"a":0,"k":{"i":[[0,-7.652],[7.652,0],[0,7.652],[-7.652,0]],"o":[[0,7.652],[-7.652,0],[0,-7.652],[7.652,0]],"v":[[13.855,0],[0,13.855],[-13.855,0],[0,-13.855]],"c":true},"ix":2},"nm":"Path 1","mn":"ADBE Vector Shape - Group","hd":false},{"ty":"fl","c":{"a":0,"k":[0.35686275363,0.72549021244,0.454901963472,1],"ix":4},"o":{"a":0,"k":100,"ix":5},"r":1,"bm":0,"nm":"Fill 1","mn":"ADBE Vector Graphic - Fill","hd":false},{"ty":"tr","p":{"a":0,"k":[206,207.055],"ix":2},"a":{"a":0,"k":[0,0],"ix":1},"s":{"a":0,"k":[100,100],"ix":3},"r":{"a":0,"k":0,"ix":6},"o":{"a":0,"k":100,"ix":7},"sk":{"a":0,"k":0,"ix":4},"sa":{"a":0,"k":0,"ix":5},"nm":"Transform"}],"nm":"Group 2","np":2,"cix":2,"bm":0,"ix":1,"mn":"ADBE Vector Group","hd":false}],"ip":120,"op":152,"st":120,"bm":0},{"ddd":0,"ind":5,"ty":4,"nm":".green400","cl":"green400","sr":1,"ks":{"o":{"a":1,"k":[{"i":{"x":[0.833],"y":[0.833]},"o":{"x":[0.167],"y":[0.167]},"t":124,"s":[30]},{"t":134,"s":[0]}],"ix":11},"r":{"a":0,"k":0,"ix":10},"p":{"a":0,"k":[206,207.055,0],"ix":2,"l":2},"a":{"a":0,"k":[206,207.055,0],"ix":1,"l":2},"s":{"a":1,"k":[{"i":{"x":[0,0,0.667],"y":[1,1,1]},"o":{"x":[0.167,0.167,0.167],"y":[0.167,0.167,-0.521]},"t":102,"s":[100,100,100]},{"t":134,"s":[155,155,100]}],"ix":6,"l":2}},"ao":0,"shapes":[{"ty":"gr","it":[{"ind":0,"ty":"sh","ix":1,"ks":{"a":0,"k":{"i":[[0,-7.652],[7.652,0],[0,7.652],[-7.652,0]],"o":[[0,7.652],[-7.652,0],[0,-7.652],[7.652,0]],"v":[[13.855,0],[0,13.855],[-13.855,0],[0,-13.855]],"c":true},"ix":2},"nm":"Path 1","mn":"ADBE Vector Shape - Group","hd":false},{"ty":"fl","c":{"a":0,"k":[0.35686275363,0.72549021244,0.454901963472,1],"ix":4},"o":{"a":0,"k":100,"ix":5},"r":1,"bm":0,"nm":"Fill 1","mn":"ADBE Vector Graphic - Fill","hd":false},{"ty":"tr","p":{"a":0,"k":[206,207.055],"ix":2},"a":{"a":0,"k":[0,0],"ix":1},"s":{"a":0,"k":[100,100],"ix":3},"r":{"a":0,"k":0,"ix":6},"o":{"a":0,"k":100,"ix":7},"sk":{"a":0,"k":0,"ix":4},"sa":{"a":0,"k":0,"ix":5},"nm":"Transform"}],"nm":"Group 2","np":2,"cix":2,"bm":0,"ix":1,"mn":"ADBE Vector Group","hd":false}],"ip":102,"op":134,"st":102,"bm":0},{"ddd":0,"ind":6,"ty":4,"nm":".green400","cl":"green400","sr":1,"ks":{"o":{"a":1,"k":[{"i":{"x":[0.833],"y":[0.833]},"o":{"x":[0.167],"y":[0.167]},"t":87,"s":[30]},{"t":97,"s":[0]}],"ix":11},"r":{"a":0,"k":0,"ix":10},"p":{"a":0,"k":[206,207.055,0],"ix":2,"l":2},"a":{"a":0,"k":[206,207.055,0],"ix":1,"l":2},"s":{"a":1,"k":[{"i":{"x":[0,0,0.667],"y":[1,1,1]},"o":{"x":[0.167,0.167,0.167],"y":[0.167,0.167,-1.905]},"t":65,"s":[100,100,100]},{"t":97,"s":[155,155,100]}],"ix":6,"l":2}},"ao":0,"shapes":[{"ty":"gr","it":[{"ind":0,"ty":"sh","ix":1,"ks":{"a":0,"k":{"i":[[0,-7.652],[7.652,0],[0,7.652],[-7.652,0]],"o":[[0,7.652],[-7.652,0],[0,-7.652],[7.652,0]],"v":[[13.855,0],[0,13.855],[-13.855,0],[0,-13.855]],"c":true},"ix":2},"nm":"Path 1","mn":"ADBE Vector Shape - Group","hd":false},{"ty":"fl","c":{"a":0,"k":[0.35686275363,0.72549021244,0.454901963472,1],"ix":4},"o":{"a":0,"k":100,"ix":5},"r":1,"bm":0,"nm":"Fill 1","mn":"ADBE Vector Graphic - Fill","hd":false},{"ty":"tr","p":{"a":0,"k":[206,207.055],"ix":2},"a":{"a":0,"k":[0,0],"ix":1},"s":{"a":0,"k":[100,100],"ix":3},"r":{"a":0,"k":0,"ix":6},"o":{"a":0,"k":100,"ix":7},"sk":{"a":0,"k":0,"ix":4},"sa":{"a":0,"k":0,"ix":5},"nm":"Transform"}],"nm":"Group 2","np":2,"cix":2,"bm":0,"ix":1,"mn":"ADBE Vector Group","hd":false}],"ip":65,"op":97,"st":65,"bm":0},{"ddd":0,"ind":7,"ty":4,"nm":".green400","cl":"green400","sr":1,"ks":{"o":{"a":1,"k":[{"i":{"x":[0.833],"y":[0.833]},"o":{"x":[0.167],"y":[0.167]},"t":70,"s":[30]},{"t":80,"s":[0]}],"ix":11},"r":{"a":0,"k":0,"ix":10},"p":{"a":0,"k":[206,207.055,0],"ix":2,"l":2},"a":{"a":0,"k":[206,207.055,0],"ix":1,"l":2},"s":{"a":1,"k":[{"i":{"x":[0,0,0.667],"y":[1,1,1]},"o":{"x":[0.167,0.167,0.167],"y":[0.167,0.167,-0.521]},"t":48,"s":[100,100,100]},{"t":80,"s":[155,155,100]}],"ix":6,"l":2}},"ao":0,"shapes":[{"ty":"gr","it":[{"ind":0,"ty":"sh","ix":1,"ks":{"a":0,"k":{"i":[[0,-7.652],[7.652,0],[0,7.652],[-7.652,0]],"o":[[0,7.652],[-7.652,0],[0,-7.652],[7.652,0]],"v":[[13.855,0],[0,13.855],[-13.855,0],[0,-13.855]],"c":true},"ix":2},"nm":"Path 1","mn":"ADBE Vector Shape - Group","hd":false},{"ty":"fl","c":{"a":0,"k":[0.35686275363,0.72549021244,0.454901963472,1],"ix":4},"o":{"a":0,"k":100,"ix":5},"r":1,"bm":0,"nm":"Fill 1","mn":"ADBE Vector Graphic - Fill","hd":false},{"ty":"tr","p":{"a":0,"k":[206,207.055],"ix":2},"a":{"a":0,"k":[0,0],"ix":1},"s":{"a":0,"k":[100,100],"ix":3},"r":{"a":0,"k":0,"ix":6},"o":{"a":0,"k":100,"ix":7},"sk":{"a":0,"k":0,"ix":4},"sa":{"a":0,"k":0,"ix":5},"nm":"Transform"}],"nm":"Group 2","np":2,"cix":2,"bm":0,"ix":1,"mn":"ADBE Vector Group","hd":false}],"ip":48,"op":80,"st":48,"bm":0},{"ddd":0,"ind":8,"ty":4,"nm":".grey600","cl":"grey600","sr":1,"ks":{"o":{"a":1,"k":[{"i":{"x":[0.833],"y":[0.833]},"o":{"x":[0.167],"y":[0.167]},"t":30,"s":[0]},{"i":{"x":[0.833],"y":[0.833]},"o":{"x":[0.167],"y":[0.167]},"t":45,"s":[100]},{"i":{"x":[0.833],"y":[0.833]},"o":{"x":[0.167],"y":[0.167]},"t":160,"s":[100]},{"t":175,"s":[0]}],"ix":11},"r":{"a":0,"k":0,"ix":10},"p":{"a":1,"k":[{"i":{"x":0.1,"y":1},"o":{"x":0.167,"y":0.167},"t":30,"s":[206,172,0],"to":[0,-3.667,0],"ti":[0,3.667,0]},{"i":{"x":1,"y":1},"o":{"x":0,"y":0},"t":45,"s":[206,150,0],"to":[0,0,0],"ti":[0,0,0]},{"i":{"x":0.833,"y":0.833},"o":{"x":0.8,"y":0},"t":160,"s":[206,150,0],"to":[0,3.667,0],"ti":[0,-3.667,0]},{"t":175,"s":[206,172,0]}],"ix":2,"l":2},"a":{"a":0,"k":[0,0,0],"ix":1,"l":2},"s":{"a":0,"k":[100,100,100],"ix":6,"l":2}},"ao":0,"shapes":[{"ty":"gr","it":[{"ind":0,"ty":"sh","ix":1,"ks":{"a":0,"k":{"i":[[2.077,0],[1.842,0.607],[1.528,1.136],[-1.842,0.607],[-2.077,0],[-1.842,-0.607],[-1.528,-1.136],[1.842,-0.607]],"o":[[-2.077,0],[-1.842,-0.607],[1.528,-1.136],[1.842,-0.607],[2.077,0],[1.842,0.607],[-1.528,1.136],[-1.842,0.607]],"v":[[0.117,-46.657],[-5.76,-47.568],[-10.815,-50.183],[-5.76,-52.799],[0.117,-53.71],[5.994,-52.799],[11.049,-50.183],[5.994,-47.568]],"c":true},"ix":2},"nm":"Path 1","mn":"ADBE Vector Shape - Group","hd":false},{"ind":1,"ty":"sh","ix":2,"ks":{"a":0,"k":{"i":[[1.019,0],[0.666,0.666],[0,1.019],[-0.666,0.666],[-1.019,0],[-0.666,-0.666],[0,-1.019],[0.666,-0.666]],"o":[[-1.019,0],[-0.666,-0.666],[0,-1.019],[0.666,-0.666],[1.019,0],[0.666,0.666],[0,1.019],[-0.666,0.666]],"v":[[0.117,-67.816],[-2.41,-68.815],[-3.409,-71.342],[-2.41,-73.869],[0.117,-74.869],[2.644,-73.869],[3.643,-71.342],[2.644,-68.815]],"c":true},"ix":2},"nm":"Path 2","mn":"ADBE Vector Shape - Group","hd":false},{"ind":2,"ty":"sh","ix":3,"ks":{"a":0,"k":{"i":[[-1.019,0],[-0.666,0.666],[0,1.019],[0.666,0.666],[1.019,0],[0.666,-0.666],[0,-1.019],[-0.666,-0.666]],"o":[[1.019,0],[0.666,-0.666],[0,-1.019],[-0.666,-0.666],[-1.019,0],[-0.666,0.666],[0,1.019],[0.666,0.666]],"v":[[0.117,-67.816],[2.644,-68.815],[3.643,-71.342],[2.644,-73.869],[0.117,-74.869],[-2.41,-73.869],[-3.409,-71.342],[-2.41,-68.815]],"c":true},"ix":2},"nm":"Path 3","mn":"ADBE Vector Shape - Group","hd":false},{"ind":3,"ty":"sh","ix":4,"ks":{"a":0,"k":{"i":[[-2.077,0],[-1.842,0.607],[-1.528,1.136],[1.842,0.607],[2.077,0],[1.842,-0.607],[1.528,-1.136],[-1.842,-0.607]],"o":[[2.077,0],[1.842,-0.607],[-1.528,-1.136],[-1.842,-0.607],[-2.077,0],[-1.842,0.607],[1.528,1.136],[1.842,0.607]],"v":[[0.117,-46.657],[5.994,-47.568],[11.049,-50.183],[5.994,-52.799],[0.117,-53.71],[-5.76,-52.799],[-10.815,-50.183],[-5.76,-47.568]],"c":true},"ix":2},"nm":"Path 4","mn":"ADBE Vector Shape - Group","hd":false},{"ind":4,"ty":"sh","ix":5,"ks":{"a":0,"k":{"i":[[3.252,0],[2.86,1.234],[2.116,2.116],[1.234,2.86],[0,3.252],[-1.234,2.86],[-2.116,2.116],[-2.86,1.234],[-3.252,0],[-2.86,-1.234],[-2.116,-2.116],[-1.234,-2.86],[0,-3.252],[1.234,-2.86],[2.116,-2.116],[2.86,-1.234]],"o":[[-3.252,0],[-2.86,-1.234],[-2.116,-2.116],[-1.234,-2.86],[0,-3.252],[1.234,-2.86],[2.116,-2.116],[2.86,-1.234],[3.252,0],[2.86,1.234],[2.116,2.116],[1.234,2.86],[0,3.252],[-1.234,2.86],[-2.116,2.116],[-2.86,1.234]],"v":[[0.117,-41.955],[-9.052,-43.806],[-16.516,-48.831],[-21.541,-56.296],[-23.393,-65.465],[-21.541,-74.633],[-16.516,-82.098],[-9.052,-87.123],[0.117,-88.975],[9.286,-87.123],[16.75,-82.098],[21.775,-74.633],[23.627,-65.465],[21.775,-56.296],[16.75,-48.831],[9.286,-43.806]],"c":true},"ix":2},"nm":"Path 5","mn":"ADBE Vector Shape - Group","hd":false},{"ind":5,"ty":"sh","ix":6,"ks":{"a":0,"k":{"i":[[2.312,0],[1.587,1.587],[0,2.312],[-1.587,1.587],[-2.312,0],[-1.587,-1.587],[0,-2.312],[1.587,-1.587]],"o":[[-2.312,0],[-1.587,-1.587],[0,-2.312],[1.587,-1.587],[2.312,0],[1.587,1.587],[0,2.312],[-1.587,1.587]],"v":[[0.117,-63.114],[-5.731,-65.494],[-8.111,-71.342],[-5.731,-77.19],[0.117,-79.571],[5.965,-77.19],[8.345,-71.342],[5.965,-65.494]],"c":true},"ix":2},"nm":"Path 6","mn":"ADBE Vector Shape - Group","hd":false},{"ind":6,"ty":"sh","ix":7,"ks":{"a":0,"k":{"i":[[-1.371,-1.607],[-2.469,0.882],[-2.704,0],[-2.469,-0.882],[-1.998,-1.528],[-0.764,2.038],[0,2.312],[3.664,3.664],[5.211,0],[3.664,-3.664],[0,-5.211],[-0.764,-2.038]],"o":[[1.998,-1.528],[2.469,-0.882],[2.704,0],[2.469,0.882],[1.371,-1.607],[0.764,-2.038],[0,-5.211],[-3.664,-3.664],[-5.211,0],[-3.664,3.664],[0,2.312],[0.764,2.038]],"v":[[-14.342,-53.475],[-7.641,-57.089],[0.117,-58.412],[7.875,-57.089],[14.576,-53.475],[17.779,-58.941],[18.925,-65.465],[13.429,-78.777],[0.117,-84.273],[-13.195,-78.777],[-18.691,-65.465],[-17.545,-58.941]],"c":true},"ix":2},"nm":"Path 7","mn":"ADBE Vector Shape - Group","hd":false},{"ty":"fl","c":{"a":0,"k":[0.501960813999,0.525490224361,0.54509806633,1],"ix":4},"o":{"a":0,"k":100,"ix":5},"r":1,"bm":0,"nm":"Fill 1","mn":"ADBE Vector Graphic - Fill","hd":false},{"ty":"tr","p":{"a":0,"k":[0,0],"ix":2},"a":{"a":0,"k":[0,0],"ix":1},"s":{"a":0,"k":[100,100],"ix":3},"r":{"a":0,"k":0,"ix":6},"o":{"a":0,"k":100,"ix":7},"sk":{"a":0,"k":0,"ix":4},"sa":{"a":0,"k":0,"ix":5},"nm":"Transform"}],"nm":"Group 1","np":8,"cix":2,"bm":0,"ix":1,"mn":"ADBE Vector Group","hd":false}],"ip":0,"op":360,"st":0,"bm":0},{"ddd":0,"ind":9,"ty":4,"nm":"Fingers","sr":1,"ks":{"o":{"a":0,"k":100,"ix":11},"r":{"a":1,"k":[{"i":{"x":[0.609],"y":[0.736]},"o":{"x":[0.5],"y":[0]},"t":120,"s":[0]},{"i":{"x":[0.699],"y":[1.002]},"o":{"x":[0.397],"y":[0.671]},"t":140,"s":[-1]},{"i":{"x":[0.48],"y":[1]},"o":{"x":[0.465],"y":[0.001]},"t":165,"s":[-1.5]},{"t":185,"s":[0]}],"ix":10},"p":{"a":0,"k":[278.083,225.939,0],"ix":2,"l":2},"a":{"a":0,"k":[602.583,604.439,0],"ix":1,"l":2},"s":{"a":0,"k":[100,100,100],"ix":6,"l":2}},"ao":0,"shapes":[{"ty":"gr","it":[{"ind":0,"ty":"sh","ix":1,"ks":{"a":1,"k":[{"i":{"x":0.7,"y":1},"o":{"x":0.5,"y":0},"t":120,"s":[{"i":[[-0.361,-6.991],[-0.942,-5.84],[1.283,-0.136],[1.676,12.257],[-0.883,2.094]],"o":[[0.127,2.412],[-0.909,1.195],[-4.055,0.442],[-0.993,-7.242],[8.742,-1.516]],"v":[[6.775,-0.884],[8.484,12.041],[5.187,14.303],[-8.044,-0.774],[-7.276,-14.15]],"c":true}]},{"i":{"x":0.52,"y":1},"o":{"x":0.28,"y":0},"t":140,"s":[{"i":[[-1.298,-6.879],[-1.714,-5.661],[1.253,-0.31],[3.301,11.923],[-0.596,2.193]],"o":[[0.448,2.374],[-0.741,1.306],[-3.96,0.979],[-1.951,-7.045],[8.462,-2.67]],"v":[[-8.516,-1.195],[-5.097,11.386],[-8.063,14.068],[-23.188,0.893],[-24.213,-12.466]],"c":true}]},{"i":{"x":0.48,"y":1},"o":{"x":0.46,"y":0},"t":165,"s":[{"i":[[-1.758,-6.776],[-2.091,-5.533],[1.229,-0.393],[4.098,11.673],[-0.447,2.228]],"o":[[0.607,2.338],[-0.652,1.353],[-3.885,1.244],[-2.421,-6.898],[8.262,-3.234]],"v":[[-14.289,-0.412],[-10.029,11.91],[-12.807,14.786],[-28.786,2.661],[-30.709,-10.599]],"c":true}]},{"t":185,"s":[{"i":[[-0.361,-6.991],[-0.942,-5.84],[1.283,-0.136],[1.676,12.257],[-0.883,2.094]],"o":[[0.127,2.412],[-0.909,1.195],[-4.055,0.442],[-0.993,-7.242],[8.742,-1.516]],"v":[[6.775,-0.884],[8.484,12.041],[5.187,14.303],[-8.044,-0.774],[-7.276,-14.15]],"c":true}]}],"ix":2},"nm":"Path 1","mn":"ADBE Vector Shape - Group","hd":false},{"ty":"fl","c":{"a":0,"k":[0.760784327984,0.478431373835,0.40000000596,1],"ix":4},"o":{"a":0,"k":100,"ix":5},"r":1,"bm":0,"nm":"Fill 1","mn":"ADBE Vector Graphic - Fill","hd":false},{"ty":"tr","p":{"a":0,"k":[607.849,490.31],"ix":2},"a":{"a":0,"k":[0,0],"ix":1},"s":{"a":0,"k":[100,100],"ix":3},"r":{"a":0,"k":0,"ix":6},"o":{"a":0,"k":100,"ix":7},"sk":{"a":0,"k":0,"ix":4},"sa":{"a":0,"k":0,"ix":5},"nm":"Transform"}],"nm":"Group 1","np":2,"cix":2,"bm":0,"ix":1,"mn":"ADBE Vector Group","hd":false},{"ty":"gr","it":[{"ind":0,"ty":"sh","ix":1,"ks":{"a":1,"k":[{"i":{"x":0.7,"y":1},"o":{"x":0.5,"y":0},"t":120,"s":[{"i":[[-3.157,-11.883],[11.468,-23.347],[6.392,14.109],[-14.557,34.418],[1.773,16.015],[-11.824,6.002],[-1.532,0.264],[-0.993,-7.242],[-4.055,0.442],[-0.909,1.195]],"o":[[4.483,16.782],[-11.468,23.347],[-6.378,-14.108],[0,0],[-1.773,-16.015],[1.77,-0.896],[-0.883,2.094],[1.676,12.257],[1.283,-0.136],[2.296,14.141]],"v":[[24.849,-10.225],[22.782,68.822],[-26.274,69.538],[-16.548,-6.081],[-12.06,-32.385],[-5.463,-81.656],[-0.51,-83.375],[-1.278,-69.998],[11.953,-54.922],[15.25,-57.184]],"c":true}]},{"i":{"x":0.52,"y":1},"o":{"x":0.28,"y":0},"t":140,"s":[{"i":[[-3.164,-11.881],[11.468,-23.347],[6.392,14.109],[-12.28,31.966],[6.09,15.085],[-10.927,7.513],[-1.483,0.466],[-1.948,-7.046],[-3.963,0.967],[-0.741,1.306]],"o":[[5.017,18.842],[-11.468,23.347],[-6.378,-14.108],[3.19,-8.303],[-6.032,-14.942],[1.635,-1.124],[-0.596,2.193],[3.297,11.924],[1.254,-0.306],[4.163,13.708]],"v":[[17.451,-12.582],[22.782,68.822],[-26.274,69.538],[-23.022,-2.948],[-22.086,-29.616],[-22.126,-79.327],[-17.447,-81.691],[-16.422,-68.332],[-1.297,-55.157],[1.669,-57.839]],"c":true}]},{"i":{"x":0.48,"y":1},"o":{"x":0.46,"y":0},"t":165,"s":[{"i":[[-3.958,-11.641],[11.468,-23.347],[6.392,14.109],[-7.395,28.547],[7.093,14.64],[-10.396,8.233],[-1.448,0.565],[-2.419,-6.898],[-3.888,1.232],[-0.652,1.353]],"o":[[6.276,18.461],[-11.468,23.347],[-6.378,-14.108],[2.231,-8.611],[-7.025,-14.501],[1.555,-1.232],[-0.447,2.228],[4.093,11.675],[1.23,-0.39],[5.078,13.396]],"v":[[15.534,-13.224],[22.782,68.822],[-26.274,69.538],[-24.197,-0.884],[-25.061,-27.555],[-28.452,-77.149],[-23.943,-79.824],[-22.02,-66.564],[-6.041,-54.439],[-3.263,-57.315]],"c":true}]},{"t":185,"s":[{"i":[[-3.157,-11.883],[11.468,-23.347],[6.392,14.109],[-14.557,34.418],[1.773,16.016],[-11.824,6.002],[-1.532,0.264],[-0.993,-7.242],[-4.055,0.442],[-0.909,1.195]],"o":[[4.483,16.782],[-11.468,23.347],[-6.378,-14.108],[0,0],[-1.773,-16.015],[1.77,-0.896],[-0.883,2.094],[1.676,12.257],[1.283,-0.136],[2.296,14.141]],"v":[[24.849,-10.225],[22.782,68.822],[-26.274,69.538],[-16.548,-6.081],[-12.06,-32.385],[-5.463,-81.656],[-0.51,-83.375],[-1.278,-69.998],[11.953,-54.922],[15.25,-57.184]],"c":true}]}],"ix":2},"nm":"Path 1","mn":"ADBE Vector Shape - Group","hd":false},{"ty":"fl","c":{"a":0,"k":[0.678431391716,0.403921574354,0.305882364511,1],"ix":4},"o":{"a":0,"k":100,"ix":5},"r":1,"bm":0,"nm":"Fill 1","mn":"ADBE Vector Graphic - Fill","hd":false},{"ty":"tr","p":{"a":0,"k":[601.083,559.534],"ix":2},"a":{"a":0,"k":[0,0],"ix":1},"s":{"a":0,"k":[100,100],"ix":3},"r":{"a":0,"k":0,"ix":6},"o":{"a":0,"k":100,"ix":7},"sk":{"a":0,"k":0,"ix":4},"sa":{"a":0,"k":0,"ix":5},"nm":"Transform"}],"nm":"Group 2","np":2,"cix":2,"bm":0,"ix":2,"mn":"ADBE Vector Group","hd":false}],"ip":0,"op":360,"st":0,"bm":0},{"ddd":0,"ind":10,"ty":4,"nm":"Fingers 2","sr":1,"ks":{"o":{"a":0,"k":100,"ix":11},"r":{"a":0,"k":0,"ix":10},"p":{"a":0,"k":[141.894,161.017,0],"ix":2,"l":2},"a":{"a":0,"k":[466.394,539.517,0],"ix":1,"l":2},"s":{"a":0,"k":[100,100,100],"ix":6,"l":2}},"ao":0,"shapes":[{"ty":"gr","it":[{"ind":0,"ty":"sh","ix":1,"ks":{"a":1,"k":[{"i":{"x":0.7,"y":1},"o":{"x":0.5,"y":0},"t":120,"s":[{"i":[[0,0],[1.006,-1.676],[-6.732,-5.567],[1.235,5.92],[0,0],[0,1.694],[-0.582,1.747],[0,0],[-1.42,2.409],[0,0]],"o":[[1.668,1.023],[-3.176,5.303],[-3.353,-2.012],[0,0],[-0.45,-1.544],[0,-1.95],[0,0],[0,0],[0,0],[0,0]],"v":[[0.049,-12.158],[1.734,-7.244],[4.231,13.075],[-3.534,1.694],[-3.534,1.65],[-4.231,-3.22],[-3.322,-8.779],[-3.322,-8.814],[-1.451,-13.075],[-1.443,-13.075]],"c":true}]},{"i":{"x":0.52,"y":1},"o":{"x":0.28,"y":0},"t":139,"s":[{"i":[[-0.695,-0.208],[0.18,-1.947],[-5.719,-5.383],[2.827,5.621],[0,0],[0.281,1.67],[-0.582,1.747],[0,0],[-1.42,2.409],[0,0]],"o":[[3.051,0.915],[-0.508,5.489],[-3.64,-1.427],[0,0],[-0.7,-1.448],[-0.324,-1.923],[0,0],[0,0],[0,0],[0,0]],"v":[[0.017,-11.533],[4.045,-7.138],[9.881,12.484],[-1.54,2.605],[-1.547,2.562],[-3.043,-2.125],[-3.322,-8.779],[-3.322,-8.814],[-2.326,-11.482],[-2.13,-11.888]],"c":true}]},{"i":{"x":0.48,"y":1},"o":{"x":0.46,"y":0},"t":165,"s":[{"i":[[-0.694,-0.212],[-0.02,-1.955],[-5.095,-5.081],[2.827,5.621],[0,0],[0.281,1.67],[-0.582,1.747],[0,0],[-0.824,1.926],[0,0]],"o":[[2.583,0.79],[0.055,5.364],[-3.705,-1.25],[0,0],[-0.7,-1.448],[-0.324,-1.923],[0,0],[0,0],[0,0],[0,0]],"v":[[0.174,-11.095],[4.045,-7.138],[10.249,11.868],[-1.54,2.605],[-1.547,2.562],[-3.043,-2.125],[-3.322,-8.779],[-3.322,-8.814],[-2.514,-11.013],[-2.318,-11.388]],"c":true}]},{"t":185,"s":[{"i":[[0,0],[1.006,-1.676],[-6.732,-5.567],[1.235,5.92],[0,0],[0,1.694],[-0.582,1.747],[0,0],[-1.421,2.409],[0,0]],"o":[[1.668,1.023],[-3.176,5.302],[-3.353,-2.012],[0,0],[-0.45,-1.544],[0,-1.95],[0,0],[0,0],[0,0],[0,0]],"v":[[0.049,-12.158],[1.734,-7.244],[4.231,13.075],[-3.534,1.694],[-3.534,1.65],[-4.231,-3.22],[-3.322,-8.779],[-3.322,-8.814],[-1.451,-13.075],[-1.443,-13.075]],"c":true}]}],"ix":2},"nm":"Path 1","mn":"ADBE Vector Shape - Group","hd":false},{"ty":"fl","c":{"a":0,"k":[0.760784327984,0.478431373835,0.40000000596,1],"ix":4},"o":{"a":0,"k":100,"ix":5},"r":1,"bm":0,"nm":"Fill 1","mn":"ADBE Vector Graphic - Fill","hd":false},{"ty":"tr","p":{"a":0,"k":[455.088,543.274],"ix":2},"a":{"a":0,"k":[0,0],"ix":1},"s":{"a":0,"k":[100,100],"ix":3},"r":{"a":0,"k":0,"ix":6},"o":{"a":0,"k":100,"ix":7},"sk":{"a":0,"k":0,"ix":4},"sa":{"a":0,"k":0,"ix":5},"nm":"Transform"}],"nm":"Group 1","np":2,"cix":2,"bm":0,"ix":1,"mn":"ADBE Vector Group","hd":false},{"ty":"gr","it":[{"ind":0,"ty":"sh","ix":1,"ks":{"a":1,"k":[{"i":{"x":0.7,"y":1},"o":{"x":0.5,"y":0},"t":120,"s":[{"i":[[6.76,1.117],[0,0],[0.119,-0.012],[0,0],[0.284,-0.052],[0.236,-0.048],[0.115,-0.026],[0.308,-0.09],[1.994,-3.367],[0,0],[0,0],[0,-1.95],[-0.45,-1.544],[0,0],[-3.353,-2.012],[-3.159,0],[-0.229,0.018],[0,0],[0,0],[0,7.191]],"o":[[0,0],[-0.12,0.01],[0,0],[-0.293,0.045],[-0.24,0.038],[-0.116,0.025],[-0.315,0.072],[-7.256,1.915],[-1.42,2.409],[0,0],[-0.582,1.747],[0,1.694],[0,0],[1.235,5.92],[2.365,1.747],[0.238,0],[0.75,0.053],[0,0],[6.935,-0.926],[0,-7.066]],"v":[[3.61,-9.409],[3.61,-19.633],[3.256,-19.587],[3.256,-19.631],[2.402,-19.475],[1.689,-19.345],[1.347,-19.267],[0.409,-19.035],[-12.758,-9.317],[-14.628,-5.056],[-14.628,-5.02],[-15.537,0.538],[-14.84,5.408],[-14.84,5.452],[-7.076,16.834],[1.359,19.631],[2.056,19.595],[3.256,19.631],[3.256,19.49],[15.537,5.452]],"c":true}]},{"i":{"x":0.52,"y":1},"o":{"x":0.28,"y":0},"t":139,"s":[{"i":[[6.851,-0.021],[0,0],[0.119,-0.012],[0,0],[0.284,-0.052],[0.236,-0.048],[0.115,-0.026],[0.308,-0.09],[1.994,-3.367],[0,0],[0,0],[-0.324,-1.923],[-0.7,-1.448],[0,0],[-3.64,-1.427],[-3.115,0.524],[-0.223,0.056],[0,0],[0,0],[1.194,7.091]],"o":[[0,0],[-0.12,0.01],[0,0],[-0.293,0.045],[-0.24,0.038],[-0.116,0.025],[-0.315,0.072],[-7.256,1.915],[-1.42,2.409],[0,0],[-0.582,1.747],[0.281,1.67],[0,0],[2.201,5.633],[2.622,1.33],[0.235,-0.04],[0.748,-0.072],[0,0],[6.685,-2.065],[-1.173,-6.968]],"v":[[3.755,-11.855],[3.61,-19.633],[3.256,-19.587],[3.256,-19.631],[2.402,-19.475],[1.689,-19.345],[1.347,-19.267],[0.409,-19.035],[-12.758,-9.317],[-14.628,-5.056],[-14.628,-5.02],[-14.35,1.633],[-12.854,6.32],[-12.846,6.363],[-1.425,16.242],[7.357,17.6],[8.038,17.449],[9.227,17.285],[9.204,17.146],[18.984,1.264]],"c":true}]},{"i":{"x":0.48,"y":1},"o":{"x":0.46,"y":0},"t":165,"s":[{"i":[[6.842,-0.352],[0,0],[0.119,-0.012],[0,0],[0.284,-0.052],[0.236,-0.048],[0.115,-0.026],[0.308,-0.09],[1.994,-3.367],[0,0],[0,0],[-0.324,-1.923],[-0.7,-1.448],[0,0],[-3.705,-1.25],[-3.086,0.674],[-0.22,0.066],[0,0],[0,0],[1.535,7.025]],"o":[[0,0],[-0.12,0.01],[0,0],[-0.293,0.045],[-0.24,0.038],[-0.116,0.025],[-0.315,0.072],[-7.256,1.915],[-1.42,2.409],[0,0],[-0.582,1.747],[0.281,1.67],[0,0],[2.201,5.633],[2.683,1.202],[0.233,-0.051],[0.744,-0.108],[0,0],[6.577,-2.385],[-1.508,-6.904]],"v":[[3.618,-12.342],[3.61,-19.633],[3.256,-19.587],[3.256,-19.631],[2.402,-19.475],[1.689,-19.345],[1.347,-19.267],[0.409,-19.035],[-12.758,-9.317],[-14.628,-5.056],[-14.628,-5.02],[-14.35,1.633],[-12.854,6.32],[-12.846,6.363],[-0.2,15.973],[9.262,16.405],[9.936,16.222],[11.116,16],[11.086,15.862],[20.088,-0.473]],"c":true}]},{"t":185,"s":[{"i":[[6.76,1.117],[0,0],[0.119,-0.013],[0,0],[0.284,-0.052],[0.236,-0.048],[0.115,-0.026],[0.308,-0.09],[1.994,-3.367],[0,0],[0,0],[0,-1.95],[-0.45,-1.544],[0,0],[-3.353,-2.012],[-3.159,0],[-0.229,0.018],[0,0],[0,0],[0,7.191]],"o":[[0,0],[-0.12,0.01],[0,0],[-0.294,0.045],[-0.24,0.038],[-0.116,0.024],[-0.315,0.072],[-7.256,1.915],[-1.42,2.409],[0,0],[-0.582,1.747],[0,1.694],[0,0],[1.235,5.92],[2.365,1.747],[0.238,0],[0.75,0.053],[0,0],[6.935,-0.926],[0,-7.066]],"v":[[3.61,-9.409],[3.61,-19.633],[3.256,-19.587],[3.256,-19.631],[2.402,-19.475],[1.689,-19.345],[1.347,-19.267],[0.409,-19.035],[-12.758,-9.317],[-14.628,-5.056],[-14.628,-5.02],[-15.537,0.538],[-14.84,5.408],[-14.84,5.452],[-7.076,16.834],[1.359,19.631],[2.056,19.595],[3.256,19.631],[3.256,19.49],[15.537,5.452]],"c":true}]}],"ix":2},"nm":"Path 1","mn":"ADBE Vector Shape - Group","hd":false},{"ty":"fl","c":{"a":0,"k":[0.678431391716,0.403921574354,0.305882364511,1],"ix":4},"o":{"a":0,"k":100,"ix":5},"r":1,"bm":0,"nm":"Fill 1","mn":"ADBE Vector Graphic - Fill","hd":false},{"ty":"tr","p":{"a":0,"k":[466.394,539.517],"ix":2},"a":{"a":0,"k":[0,0],"ix":1},"s":{"a":0,"k":[100,100],"ix":3},"r":{"a":0,"k":0,"ix":6},"o":{"a":0,"k":100,"ix":7},"sk":{"a":0,"k":0,"ix":4},"sa":{"a":0,"k":0,"ix":5},"nm":"Transform"}],"nm":"Group 3","np":2,"cix":2,"bm":0,"ix":2,"mn":"ADBE Vector Group","hd":false}],"ip":0,"op":360,"st":0,"bm":0},{"ddd":0,"ind":11,"ty":4,"nm":"Fingers 3","sr":1,"ks":{"o":{"a":0,"k":100,"ix":11},"r":{"a":0,"k":0,"ix":10},"p":{"a":0,"k":[142.527,197.263,0],"ix":2,"l":2},"a":{"a":0,"k":[467.027,575.763,0],"ix":1,"l":2},"s":{"a":0,"k":[100,100,100],"ix":6,"l":2}},"ao":0,"shapes":[{"ty":"gr","it":[{"ty":"gr","it":[{"ind":0,"ty":"sh","ix":1,"ks":{"a":1,"k":[{"i":{"x":0.833,"y":0.833},"o":{"x":0.167,"y":0.167},"t":120,"s":[{"i":[[-0.796,0.122],[0,0],[1.489,0.513],[0.561,-0.278],[-2.983,0]],"o":[[0,0],[-2.869,0.476],[-0.597,0.211],[0.987,0.473],[0.719,0]],"v":[[4.253,0.872],[4.253,-0.475],[-2.517,-1.049],[-4.253,-0.316],[1.976,1.049]],"c":true}]},{"i":{"x":0.833,"y":0.833},"o":{"x":0.167,"y":0.167},"t":135,"s":[{"i":[[-0.754,-0.033],[0,0],[0.766,0.076],[0.561,-0.278],[-1.351,-0.023]],"o":[[0,0],[-0.942,-0.061],[-2.484,0.076],[0.878,-0.032],[0.719,0.012]],"v":[[4.191,-1.566],[4.191,-1.913],[2.233,-1.987],[-0.441,-1.566],[2.351,-1.638]],"c":true}]},{"i":{"x":0.833,"y":0.833},"o":{"x":0.167,"y":0.167},"t":170,"s":[{"i":[[-0.754,-0.033],[0,0],[0.766,0.076],[0.561,-0.278],[-1.351,-0.023]],"o":[[0,0],[-0.942,-0.061],[-2.484,0.076],[0.878,-0.032],[0.719,0.012]],"v":[[4.191,-1.566],[4.191,-1.913],[2.233,-1.987],[-0.441,-1.566],[2.351,-1.638]],"c":true}]},{"t":185,"s":[{"i":[[-0.796,0.122],[0,0],[1.489,0.513],[0.561,-0.278],[-2.983,0]],"o":[[0,0],[-2.869,0.476],[-0.597,0.211],[0.987,0.473],[0.719,0]],"v":[[4.253,0.872],[4.253,-0.475],[-2.517,-1.049],[-4.253,-0.316],[1.976,1.049]],"c":true}]}],"ix":2},"nm":"Path 1","mn":"ADBE Vector Shape - Group","hd":false},{"ty":"fl","c":{"a":0,"k":[0.505882382393,0.274509817362,0.219607844949,1],"ix":4},"o":{"a":0,"k":100,"ix":5},"r":1,"bm":0,"nm":"Fill 1","mn":"ADBE Vector Graphic - Fill","hd":false},{"ty":"tr","p":{"a":0,"k":[0,0],"ix":2},"a":{"a":0,"k":[0,0],"ix":1},"s":{"a":0,"k":[100,100],"ix":3},"r":{"a":0,"k":0,"ix":6},"o":{"a":1,"k":[{"i":{"x":[0.833],"y":[0.833]},"o":{"x":[0.167],"y":[0.167]},"t":130,"s":[100]},{"i":{"x":[0.833],"y":[0.833]},"o":{"x":[0.167],"y":[0.167]},"t":135,"s":[0]},{"i":{"x":[0.833],"y":[0.833]},"o":{"x":[0.167],"y":[0.167]},"t":170,"s":[0]},{"t":175,"s":[100]}],"ix":7},"sk":{"a":0,"k":0,"ix":4},"sa":{"a":0,"k":0,"ix":5},"nm":"Transform"}],"nm":"Group 1","np":2,"cix":2,"bm":0,"ix":1,"mn":"ADBE Vector Group","hd":false},{"ty":"tr","p":{"a":0,"k":[465.751,559.349],"ix":2},"a":{"a":0,"k":[0,0],"ix":1},"s":{"a":0,"k":[100,100],"ix":3},"r":{"a":0,"k":0,"ix":6},"o":{"a":0,"k":100,"ix":7},"sk":{"a":0,"k":0,"ix":4},"sa":{"a":0,"k":0,"ix":5},"nm":"Transform"}],"nm":"Group 1","np":1,"cix":2,"bm":0,"ix":1,"mn":"ADBE Vector Group","hd":false},{"ty":"gr","it":[{"ty":"gr","it":[{"ind":0,"ty":"sh","ix":1,"ks":{"a":1,"k":[{"i":{"x":0.7,"y":1},"o":{"x":0.5,"y":0},"t":120,"s":[{"i":[[2.051,-0.571],[0,0],[-1.985,-0.332],[0,0]],"o":[[0,0],[1.936,-0.539],[0,0],[-2.108,-0.321]],"v":[[-3.074,-0.618],[-2.719,0.657],[3.262,0.358],[3.262,-0.98]],"c":true}]},{"i":{"x":0.52,"y":1},"o":{"x":0.28,"y":0},"t":139,"s":[{"i":[[1.394,-1.546],[0,0],[-1.627,-0.04],[0,0]],"o":[[0,0],[1.348,-1.202],[0,0],[-2.096,-0.202]],"v":[[-2.447,-2.604],[-1.651,-1.605],[3.418,-3.517],[3.418,-4.855]],"c":true}]},{"i":{"x":0.48,"y":1},"o":{"x":0.46,"y":0},"t":165,"s":[{"i":[[1.394,-1.546],[0,0],[-1.627,-0.04],[0,0]],"o":[[0,0],[1.348,-1.202],[0,0],[-2.096,-0.202]],"v":[[-2.572,-3.198],[-1.776,-2.199],[3.293,-4.111],[3.293,-5.448]],"c":true}]},{"t":185,"s":[{"i":[[2.051,-0.571],[0,0],[-1.985,-0.332],[0,0]],"o":[[0,0],[1.936,-0.539],[0,0],[-2.108,-0.321]],"v":[[-3.074,-0.618],[-2.719,0.657],[3.262,0.358],[3.262,-0.98]],"c":true}]}],"ix":2},"nm":"Path 1","mn":"ADBE Vector Shape - Group","hd":false},{"ty":"fl","c":{"a":0,"k":[0.505882382393,0.274509817362,0.219607844949,1],"ix":4},"o":{"a":0,"k":100,"ix":5},"r":1,"bm":0,"nm":"Fill 1","mn":"ADBE Vector Graphic - Fill","hd":false},{"ty":"tr","p":{"a":0,"k":[0,0],"ix":2},"a":{"a":0,"k":[0,0],"ix":1},"s":{"a":0,"k":[100,100],"ix":3},"r":{"a":0,"k":0,"ix":6},"o":{"a":0,"k":100,"ix":7},"sk":{"a":0,"k":0,"ix":4},"sa":{"a":0,"k":0,"ix":5},"nm":"Transform"}],"nm":"Group 1","np":2,"cix":2,"bm":0,"ix":1,"mn":"ADBE Vector Group","hd":false},{"ty":"tr","p":{"a":0,"k":[466.741,564.807],"ix":2},"a":{"a":0,"k":[0,0],"ix":1},"s":{"a":0,"k":[100,100],"ix":3},"r":{"a":0,"k":0,"ix":6},"o":{"a":0,"k":100,"ix":7},"sk":{"a":0,"k":0,"ix":4},"sa":{"a":0,"k":0,"ix":5},"nm":"Transform"}],"nm":"Group 2","np":1,"cix":2,"bm":0,"ix":2,"mn":"ADBE Vector Group","hd":false},{"ty":"gr","it":[{"ind":0,"ty":"sh","ix":1,"ks":{"a":1,"k":[{"i":{"x":0.7,"y":1},"o":{"x":0.5,"y":0},"t":120,"s":[{"i":[[0,0],[1.006,-1.676],[-6.732,-5.567],[1.235,5.92],[0,0],[0,1.694],[-0.582,1.747],[0,0],[-1.421,2.409],[0,0]],"o":[[1.668,1.023],[-3.176,5.302],[-3.353,-2.012],[0,0],[-0.45,-1.544],[0,-1.95],[0,0],[0,0],[0,0],[0,0]],"v":[[0.049,-12.158],[1.734,-7.244],[4.231,13.075],[-3.534,1.694],[-3.534,1.65],[-4.231,-3.22],[-3.322,-8.779],[-3.322,-8.814],[-1.451,-13.075],[-1.443,-13.075]],"c":true}]},{"i":{"x":0.52,"y":1},"o":{"x":0.28,"y":0},"t":139,"s":[{"i":[[-0.695,-0.208],[0.18,-1.947],[-5.719,-5.383],[2.827,5.621],[0,0],[0.281,1.67],[-0.582,1.747],[0,0],[-1.421,2.409],[0,0]],"o":[[3.051,0.915],[-0.508,5.489],[-3.64,-1.427],[0,0],[-0.7,-1.448],[-0.324,-1.923],[0,0],[0,0],[0,0],[0,0]],"v":[[0.017,-11.533],[4.045,-7.138],[9.881,12.484],[-1.54,2.605],[-1.547,2.562],[-3.043,-2.125],[-3.322,-8.779],[-3.322,-8.814],[-2.326,-11.482],[-2.13,-11.888]],"c":true}]},{"i":{"x":0.48,"y":1},"o":{"x":0.46,"y":0},"t":165,"s":[{"i":[[-0.694,-0.212],[-0.02,-1.955],[-5.095,-5.081],[2.827,5.621],[0,0],[0.281,1.67],[-0.582,1.747],[0,0],[-0.824,1.926],[0,0]],"o":[[2.583,0.79],[0.055,5.364],[-3.705,-1.25],[0,0],[-0.7,-1.448],[-0.324,-1.923],[0,0],[0,0],[0,0],[0,0]],"v":[[0.174,-11.095],[4.045,-7.138],[10.249,11.868],[-1.54,2.605],[-1.547,2.562],[-3.043,-2.125],[-3.322,-8.779],[-3.322,-8.814],[-2.514,-11.013],[-2.318,-11.388]],"c":true}]},{"t":185,"s":[{"i":[[0,0],[1.006,-1.676],[-6.732,-5.567],[1.235,5.92],[0,0],[0,1.694],[-0.582,1.747],[0,0],[-1.421,2.409],[0,0]],"o":[[1.668,1.023],[-3.176,5.302],[-3.353,-2.012],[0,0],[-0.45,-1.544],[0,-1.95],[0,0],[0,0],[0,0],[0,0]],"v":[[0.049,-12.158],[1.734,-7.244],[4.231,13.075],[-3.534,1.694],[-3.534,1.65],[-4.231,-3.22],[-3.322,-8.779],[-3.322,-8.814],[-1.451,-13.075],[-1.443,-13.075]],"c":true}]}],"ix":2},"nm":"Path 1","mn":"ADBE Vector Shape - Group","hd":false},{"ty":"fl","c":{"a":0,"k":[0.760784327984,0.478431373835,0.40000000596,1],"ix":4},"o":{"a":0,"k":100,"ix":5},"r":1,"bm":0,"nm":"Fill 1","mn":"ADBE Vector Graphic - Fill","hd":false},{"ty":"tr","p":{"a":0,"k":[455.088,578.357],"ix":2},"a":{"a":0,"k":[0,0],"ix":1},"s":{"a":0,"k":[100,100],"ix":3},"r":{"a":0,"k":0,"ix":6},"o":{"a":0,"k":100,"ix":7},"sk":{"a":0,"k":0,"ix":4},"sa":{"a":0,"k":0,"ix":5},"nm":"Transform"}],"nm":"Group 5","np":2,"cix":2,"bm":0,"ix":3,"mn":"ADBE Vector Group","hd":false},{"ty":"gr","it":[{"ind":0,"ty":"sh","ix":1,"ks":{"a":1,"k":[{"i":{"x":0.7,"y":1},"o":{"x":0.5,"y":0},"t":120,"s":[{"i":[[6.76,1.117],[0,0],[1.053,-0.142],[1.994,-3.367],[0,0],[0,0],[0,-1.95],[-0.45,-1.544],[0,0],[-3.353,-2.012],[-3.516,0.532],[0,7.191]],"o":[[0,0],[-0.12,0.01],[-7.178,0.968],[-1.42,2.409],[0,0],[-0.582,1.747],[0,1.694],[0,0],[1.235,5.92],[2.365,1.747],[7.6,-1.151],[0,-7.066]],"v":[[3.61,-9.409],[3.597,-17.665],[0.411,-17.535],[-12.758,-9.317],[-14.628,-5.056],[-14.628,-5.02],[-15.537,0.538],[-14.84,5.408],[-14.84,5.452],[-7.076,16.834],[3.256,19.49],[15.537,5.452]],"c":true}]},{"i":{"x":0.52,"y":1},"o":{"x":0.28,"y":0},"t":139,"s":[{"i":[[8.158,-0.244],[0,0],[1.097,-0.137],[1.994,-3.367],[0,0],[0,0],[-0.324,-1.923],[-0.7,-1.448],[0,0],[-3.64,-1.427],[-3.212,1.513],[0.862,7.139]],"o":[[0,0],[-0.12,0.01],[-8.013,0.999],[-1.42,2.409],[0,0],[-0.582,1.747],[0.281,1.67],[0,0],[2.201,5.633],[2.622,1.33],[5.959,-2.807],[-1.071,-8.863]],"v":[[3.76,-13.355],[3.611,-17.821],[0.432,-17.785],[-12.758,-9.317],[-14.628,-5.056],[-14.628,-5.02],[-14.35,1.633],[-12.854,6.32],[-12.846,6.363],[-1.425,16.242],[10.521,15.458],[18.989,-0.236]],"c":true}]},{"i":{"x":0.48,"y":1},"o":{"x":0.46,"y":0},"t":165,"s":[{"i":[[7.807,-0.257],[0,0],[1.077,-0.135],[1.994,-3.367],[0,0],[0,0],[-0.324,-1.923],[-0.7,-1.448],[0,0],[-5.057,-1.566],[-4.246,1.663],[0.767,7.15]],"o":[[0,0],[-0.12,0.01],[-8.217,1.03],[-1.42,2.409],[0,0],[-0.582,1.747],[0.281,1.67],[0,0],[2.14,5.038],[3.806,1.178],[5.645,-2.211],[-0.982,-9.153]],"v":[[3.611,-13.904],[3.597,-17.852],[0.386,-17.754],[-12.758,-9.317],[-14.628,-5.056],[-14.628,-5.02],[-14.35,1.633],[-12.854,6.32],[-12.846,6.363],[-0.2,15.973],[11.086,15.487],[19.338,-0.696]],"c":true}]},{"t":185,"s":[{"i":[[6.76,1.117],[0,0],[1.055,-0.127],[1.994,-3.367],[0,0],[0,0],[0,-1.95],[-0.45,-1.544],[0,0],[-3.353,-2.012],[-5.525,0.349],[0,7.191]],"o":[[0,0],[-0.12,0.01],[-7.243,0.874],[-1.42,2.409],[0,0],[-0.582,1.747],[0,1.694],[0,0],[1.235,5.92],[2.744,1.567],[7.494,-0.473],[0,-7.066]],"v":[[3.61,-9.409],[3.595,-17.946],[0.412,-17.785],[-12.758,-9.317],[-14.628,-5.056],[-14.628,-5.02],[-15.537,0.538],[-14.84,5.408],[-14.84,5.452],[-7.076,16.834],[3.256,19.49],[15.537,5.452]],"c":true}]}],"ix":2},"nm":"Path 1","mn":"ADBE Vector Shape - Group","hd":false},{"ty":"fl","c":{"a":0,"k":[0.678431391716,0.403921574354,0.305882364511,1],"ix":4},"o":{"a":0,"k":100,"ix":5},"r":1,"bm":0,"nm":"Fill 1","mn":"ADBE Vector Graphic - Fill","hd":false},{"ty":"tr","p":{"a":0,"k":[466.394,574.599],"ix":2},"a":{"a":0,"k":[0,0],"ix":1},"s":{"a":0,"k":[100,100],"ix":3},"r":{"a":0,"k":0,"ix":6},"o":{"a":0,"k":100,"ix":7},"sk":{"a":0,"k":0,"ix":4},"sa":{"a":0,"k":0,"ix":5},"nm":"Transform"}],"nm":"Group 6","np":2,"cix":2,"bm":0,"ix":4,"mn":"ADBE Vector Group","hd":false}],"ip":0,"op":360,"st":0,"bm":0},{"ddd":0,"ind":12,"ty":4,"nm":"Fingers 4","sr":1,"ks":{"o":{"a":0,"k":100,"ix":11},"r":{"a":0,"k":0,"ix":10},"p":{"a":0,"k":[144.038,222.611,0],"ix":2,"l":2},"a":{"a":0,"k":[468.538,601.111,0],"ix":1,"l":2},"s":{"a":0,"k":[100,100,100],"ix":6,"l":2}},"ao":0,"shapes":[{"ty":"gr","it":[{"ind":0,"ty":"sh","ix":1,"ks":{"a":1,"k":[{"i":{"x":0.7,"y":1},"o":{"x":0.5,"y":0},"t":120,"s":[{"i":[[-0.543,-0.756],[-0.243,-2.544],[-7.056,-2.999],[2.396,2.945],[0.28,1.671],[-0.686,2.714]],"o":[[0.751,1.046],[0.472,4.945],[-3.243,-0.624],[-1.98,-2.434],[-0.322,-1.923],[0,0]],"v":[[-0.451,-9.783],[0.577,-4.931],[9.168,8.95],[0.841,4.506],[-2.856,-3.72],[-3.045,-10.919]],"c":true}]},{"i":{"x":0.52,"y":1},"o":{"x":0.28,"y":0},"t":139,"s":[{"i":[[-1.249,-0.454],[-0.822,-2.42],[-4.118,-3.374],[2.396,2.945],[0.718,1.921],[0.095,3.245]],"o":[[1.211,0.44],[1.722,5.07],[-3.306,-0.124],[-1.98,-2.434],[-0.682,-1.827],[0,0]],"v":[[-0.451,-9.783],[3.452,-6.306],[11.793,6.263],[2.029,1.756],[-1.543,-3.97],[-2.545,-11.169]],"c":true}]},{"i":{"x":0.48,"y":1},"o":{"x":0.46,"y":0},"t":165,"s":[{"i":[[-1.249,-0.453],[-0.817,-2.422],[-4.181,-2.499],[2.646,2.82],[0.718,1.922],[0.095,3.245]],"o":[[1.211,0.44],[2.597,7.695],[-3.056,0.063],[-2.147,-2.288],[-0.682,-1.827],[0,0]],"v":[[-0.451,-9.783],[3.452,-6.306],[12.418,5.888],[2.029,1.756],[-1.543,-3.97],[-2.545,-11.169]],"c":true}]},{"t":185,"s":[{"i":[[-0.543,-0.756],[-0.243,-2.544],[-7.056,-2.999],[2.396,2.945],[0.28,1.672],[-0.686,2.714]],"o":[[0.751,1.047],[0.472,4.945],[-3.243,-0.624],[-1.98,-2.434],[-0.322,-1.923],[0,0]],"v":[[-0.451,-9.783],[0.577,-4.931],[9.168,8.95],[0.841,4.506],[-2.856,-3.72],[-3.045,-10.919]],"c":true}]}],"ix":2},"nm":"Path 1","mn":"ADBE Vector Shape - Group","hd":false},{"ty":"fl","c":{"a":0,"k":[0.760784327984,0.478431373835,0.40000000596,1],"ix":4},"o":{"a":0,"k":100,"ix":5},"r":1,"bm":0,"nm":"Fill 1","mn":"ADBE Vector Graphic - Fill","hd":false},{"ty":"tr","p":{"a":0,"k":[458.325,607.674],"ix":2},"a":{"a":0,"k":[0,0],"ix":1},"s":{"a":0,"k":[100,100],"ix":3},"r":{"a":0,"k":0,"ix":6},"o":{"a":0,"k":100,"ix":7},"sk":{"a":0,"k":0,"ix":4},"sa":{"a":0,"k":0,"ix":5},"nm":"Transform"}],"nm":"Group 5","np":2,"cix":2,"bm":0,"ix":1,"mn":"ADBE Vector Group","hd":false},{"ty":"gr","it":[{"ind":0,"ty":"sh","ix":1,"ks":{"a":1,"k":[{"i":{"x":0.7,"y":1},"o":{"x":0.5,"y":0},"t":120,"s":[{"i":[[-2.523,1.697],[0.437,0.231],[2.592,0],[2.668,3.038],[0.161,-0.462],[-1.322,-0.733],[-2.663,0]],"o":[[-0.406,-0.278],[-2.19,1.335],[-4.09,0],[-0.189,0.477],[1.071,1.114],[2.238,1.241],[3.066,0]],"v":[[9.815,0.424],[8.549,-0.338],[1.238,1.726],[-9.289,-3.049],[-9.815,-1.639],[-6.205,1.141],[1.238,3.049]],"c":true}]},{"i":{"x":0.52,"y":1},"o":{"x":0.28,"y":0},"t":139,"s":[{"i":[[-2.523,1.697],[0.437,0.231],[2.592,0],[2.668,3.038],[0.161,-0.462],[-1.322,-0.733],[-2.663,0]],"o":[[-0.406,-0.278],[-2.19,1.335],[-4.09,0],[-0.189,0.477],[1.071,1.114],[2.238,1.241],[3.066,0]],"v":[[11.44,-1.889],[10.174,-2.65],[2.863,-0.587],[-7.539,-5.174],[-8.44,-4.014],[-4.58,-1.172],[2.863,0.736]],"c":true}]},{"i":{"x":0.48,"y":1},"o":{"x":0.46,"y":0},"t":165,"s":[{"i":[[-2.523,1.697],[0.437,0.231],[2.592,0],[2.668,3.038],[0.161,-0.462],[-1.322,-0.733],[-2.663,0]],"o":[[-0.406,-0.278],[-2.19,1.335],[-4.09,0],[-0.189,0.477],[1.071,1.114],[2.238,1.241],[3.066,0]],"v":[[11.502,-1.951],[10.236,-2.713],[2.926,-0.649],[-7.476,-5.236],[-8.377,-4.077],[-4.518,-1.234],[2.926,0.674]],"c":true}]},{"t":185,"s":[{"i":[[-2.523,1.697],[0.437,0.231],[2.592,0],[2.668,3.038],[0.161,-0.462],[-1.322,-0.733],[-2.663,0]],"o":[[-0.406,-0.278],[-2.19,1.335],[-4.09,0],[-0.189,0.477],[1.071,1.114],[2.238,1.241],[3.066,0]],"v":[[9.815,0.424],[8.549,-0.338],[1.238,1.726],[-9.289,-3.049],[-9.815,-1.639],[-6.205,1.141],[1.238,3.049]],"c":true}]}],"ix":2},"nm":"Path 1","mn":"ADBE Vector Shape - Group","hd":false},{"ty":"fl","c":{"a":0,"k":[0.505882382393,0.274509817362,0.219607844949,1],"ix":4},"o":{"a":0,"k":100,"ix":5},"r":1,"bm":0,"nm":"Fill 1","mn":"ADBE Vector Graphic - Fill","hd":false},{"ty":"tr","p":{"a":0,"k":[466.549,592.429],"ix":2},"a":{"a":0,"k":[0,0],"ix":1},"s":{"a":0,"k":[100,100],"ix":3},"r":{"a":0,"k":0,"ix":6},"o":{"a":0,"k":100,"ix":7},"sk":{"a":0,"k":0,"ix":4},"sa":{"a":0,"k":0,"ix":5},"nm":"Transform"}],"nm":"Group 1","np":2,"cix":2,"bm":0,"ix":2,"mn":"ADBE Vector Group","hd":false},{"ty":"gr","it":[{"ind":0,"ty":"sh","ix":1,"ks":{"a":1,"k":[{"i":{"x":0.7,"y":1},"o":{"x":0.5,"y":0},"t":120,"s":[{"i":[[3.433,2.35],[3.066,0],[2.895,0.327],[0.417,-1.162],[0,0],[0,0],[-4.939,0],[0,7.204]],"o":[[-3.988,-2.353],[-2.633,0],[-1.53,-0.173],[-4.109,11.46],[0,0],[2.214,4.048],[7.204,0],[0,-4.474]],"v":[[7.825,-10.875],[-2.064,-15.312],[-9.184,-15.555],[-11.804,-12.938],[-10.981,6.145],[-10.98,6.144],[0.469,12.938],[13.513,-0.106]],"c":true}]},{"i":{"x":0.52,"y":1},"o":{"x":0.28,"y":0},"t":139,"s":[{"i":[[3.933,1.357],[3.066,0],[2.52,-1.173],[0.417,-1.162],[0,0],[0,0],[-4.763,1.307],[1.906,6.947]],"o":[[-4.469,-1.214],[-2.633,0],[-1.396,0.65],[-4.109,11.46],[0,0],[3.207,3.317],[6.947,-1.906],[-1.184,-4.315]],"v":[[5.683,-15.231],[-2.064,-15.312],[-8.246,-17.492],[-11.804,-12.938],[-7.948,6.159],[-7.948,6.158],[4.891,9.68],[14.018,-6.351]],"c":true}]},{"i":{"x":0.48,"y":1},"o":{"x":0.46,"y":0},"t":165,"s":[{"i":[[3.933,1.357],[3.066,0],[2.27,-2.423],[0.417,-1.162],[0,0],[0,0],[-4.763,1.307],[1.906,6.947]],"o":[[-4.469,-1.214],[-2.633,0],[-1.053,1.124],[-4.109,11.46],[0,0],[3.207,3.317],[6.947,-1.906],[-1.184,-4.315]],"v":[[5.683,-15.231],[-2.064,-15.312],[-9.184,-17.367],[-11.679,-13.25],[-7.948,6.159],[-7.698,5.908],[6.141,9.305],[14.768,-6.914]],"c":true}]},{"t":185,"s":[{"i":[[3.433,2.35],[3.066,0],[2.895,0.327],[0.417,-1.162],[0,0],[0,0],[-4.939,0],[0,7.204]],"o":[[-3.988,-2.353],[-2.633,0],[-1.53,-0.173],[-4.109,11.46],[0,0],[2.214,4.048],[7.204,0],[0,-4.474]],"v":[[7.825,-10.875],[-2.064,-15.312],[-9.184,-15.555],[-11.804,-12.938],[-10.981,6.145],[-10.98,6.144],[0.469,12.938],[13.513,-0.106]],"c":true}]}],"ix":2},"nm":"Path 1","mn":"ADBE Vector Shape - Group","hd":false},{"ty":"fl","c":{"a":0,"k":[0.678431391716,0.403921574354,0.305882364511,1],"ix":4},"o":{"a":0,"k":100,"ix":5},"r":1,"bm":0,"nm":"Fill 1","mn":"ADBE Vector Graphic - Fill","hd":false},{"ty":"tr","p":{"a":0,"k":[468.538,603.728],"ix":2},"a":{"a":0,"k":[0,0],"ix":1},"s":{"a":0,"k":[100,100],"ix":3},"r":{"a":0,"k":0,"ix":6},"o":{"a":0,"k":100,"ix":7},"sk":{"a":0,"k":0,"ix":4},"sa":{"a":0,"k":0,"ix":5},"nm":"Transform"}],"nm":"Group 2","np":2,"cix":2,"bm":0,"ix":3,"mn":"ADBE Vector Group","hd":false}],"ip":0,"op":360,"st":0,"bm":0},{"ddd":0,"ind":13,"ty":4,"nm":"Squeeze Gesture 4","sr":1,"ks":{"o":{"a":1,"k":[{"i":{"x":[0.833],"y":[0.833]},"o":{"x":[0.167],"y":[0.167]},"t":121,"s":[0]},{"i":{"x":[0.833],"y":[0.833]},"o":{"x":[0.167],"y":[0.167]},"t":149,"s":[100]},{"i":{"x":[0.833],"y":[0.833]},"o":{"x":[0.167],"y":[0.167]},"t":165,"s":[100]},{"t":195,"s":[0]}],"ix":11},"r":{"a":0,"k":0,"ix":10},"p":{"a":0,"k":[260.793,163.908,0],"ix":2,"l":2},"a":{"a":0,"k":[7.312,0,0],"ix":1,"l":2},"s":{"a":1,"k":[{"i":{"x":[0.836,0.836,0.833],"y":[0.92,0.92,1]},"o":{"x":[0.4,0.4,0.4],"y":[0,0,0]},"t":121,"s":[70,70,100]},{"i":{"x":[0.753,0.753,0.833],"y":[0.878,0.878,1]},"o":{"x":[0.578,0.578,0.167],"y":[0.696,0.696,0]},"t":159,"s":[116.607,116.607,100]},{"i":{"x":[0.667,0.667,0.667],"y":[1,1,1]},"o":{"x":[0.392,0.392,0.167],"y":[-0.024,-0.024,0]},"t":165,"s":[119.607,119.607,100]},{"t":195,"s":[0,0,100]}],"ix":6,"l":2}},"ao":0,"shapes":[{"ty":"gr","it":[{"ind":0,"ty":"sh","ix":1,"ks":{"a":0,"k":{"i":[[0,-10.369],[-8.743,-4.24],[0,0]],"o":[[0,10.369],[0,0],[-8.743,4.24]],"v":[[-7.386,0],[7.386,23.57],[7.386,-23.57]],"c":true},"ix":2},"nm":"Path 1","mn":"ADBE Vector Shape - Group","hd":false},{"ty":"fl","c":{"a":0,"k":[0.40000000596,0.615686297417,0.964705884457,1],"ix":4},"o":{"a":0,"k":100,"ix":5},"r":1,"bm":0,"nm":"Fill 1","mn":"ADBE Vector Graphic - Fill","hd":false},{"ty":"tr","p":{"a":0,"k":[0,0],"ix":2},"a":{"a":0,"k":[0,0],"ix":1},"s":{"a":0,"k":[100,100],"ix":3},"r":{"a":0,"k":0,"ix":6},"o":{"a":0,"k":100,"ix":7},"sk":{"a":0,"k":0,"ix":4},"sa":{"a":0,"k":0,"ix":5},"nm":"Transform"}],"nm":"Group 1","np":2,"cix":2,"bm":0,"ix":1,"mn":"ADBE Vector Group","hd":false}],"ip":0,"op":360,"st":0,"bm":0},{"ddd":0,"ind":14,"ty":4,"nm":"Squeeze Gesture 3","sr":1,"ks":{"o":{"a":1,"k":[{"i":{"x":[0.833],"y":[0.833]},"o":{"x":[0.167],"y":[0.167]},"t":121,"s":[0]},{"i":{"x":[0.833],"y":[0.833]},"o":{"x":[0.167],"y":[0.167]},"t":149,"s":[50]},{"i":{"x":[0.833],"y":[0.833]},"o":{"x":[0.167],"y":[0.167]},"t":165,"s":[50]},{"t":195,"s":[0]}],"ix":11},"r":{"a":0,"k":0,"ix":10},"p":{"a":0,"k":[260.892,163.908,0],"ix":2,"l":2},"a":{"a":0,"k":[12.125,0,0],"ix":1,"l":2},"s":{"a":1,"k":[{"i":{"x":[0.775,0.775,0.833],"y":[0.949,0.949,1]},"o":{"x":[0.4,0.4,0.4],"y":[0,0,0]},"t":121,"s":[45,45,100]},{"i":{"x":[0.759,0.759,0.833],"y":[0.856,0.856,1]},"o":{"x":[0.398,0.398,0.167],"y":[0.467,0.467,0]},"t":157,"s":[114.737,114.737,100]},{"i":{"x":[0.667,0.667,0.667],"y":[1,1,1]},"o":{"x":[0.393,0.393,0.167],"y":[-0.022,-0.022,0]},"t":165,"s":[117.737,117.737,100]},{"t":195,"s":[0,0,100]}],"ix":6,"l":2}},"ao":0,"shapes":[{"ty":"gr","it":[{"ind":0,"ty":"sh","ix":1,"ks":{"a":0,"k":{"i":[[-14.068,-4.758],[0,0],[0,0],[0,0],[0,-15.674]],"o":[[0,0],[0,0],[0,0],[-14.068,4.758],[0,15.674]],"v":[[12.099,33.73],[12.099,23.57],[12.099,-23.57],[12.099,-33.73],[-12.099,0]],"c":true},"ix":2},"nm":"Path 1","mn":"ADBE Vector Shape - Group","hd":false},{"ty":"fl","c":{"a":0,"k":[0.40000000596,0.615686297417,0.964705884457,1],"ix":4},"o":{"a":0,"k":100,"ix":5},"r":1,"bm":0,"nm":"Fill 1","mn":"ADBE Vector Graphic - Fill","hd":false},{"ty":"tr","p":{"a":0,"k":[0,0],"ix":2},"a":{"a":0,"k":[0,0],"ix":1},"s":{"a":0,"k":[100,100],"ix":3},"r":{"a":0,"k":0,"ix":6},"o":{"a":0,"k":100,"ix":7},"sk":{"a":0,"k":0,"ix":4},"sa":{"a":0,"k":0,"ix":5},"nm":"Transform"}],"nm":"Group 1","np":2,"cix":2,"bm":0,"ix":1,"mn":"ADBE Vector Group","hd":false}],"ip":0,"op":360,"st":0,"bm":0},{"ddd":0,"ind":15,"ty":4,"nm":"Squeeze Gesture 2","sr":1,"ks":{"o":{"a":1,"k":[{"i":{"x":[0.833],"y":[0.833]},"o":{"x":[0.167],"y":[0.167]},"t":121,"s":[0]},{"i":{"x":[0.833],"y":[0.833]},"o":{"x":[0.167],"y":[0.167]},"t":149,"s":[100]},{"i":{"x":[0.833],"y":[0.833]},"o":{"x":[0.167],"y":[0.167]},"t":165,"s":[100]},{"t":195,"s":[0]}],"ix":11},"r":{"a":0,"k":0,"ix":10},"p":{"a":0,"k":[147.55,163.908,0],"ix":2,"l":2},"a":{"a":0,"k":[-7.438,0,0],"ix":1,"l":2},"s":{"a":1,"k":[{"i":{"x":[0.836,0.836,0.833],"y":[0.92,0.92,1]},"o":{"x":[0.4,0.4,0.4],"y":[0,0,0]},"t":121,"s":[70,70,100]},{"i":{"x":[0.753,0.753,0.833],"y":[0.878,0.878,1]},"o":{"x":[0.578,0.578,0.167],"y":[0.696,0.696,0]},"t":159,"s":[116.607,116.607,100]},{"i":{"x":[0.667,0.667,0.667],"y":[1,1,1]},"o":{"x":[0.392,0.392,0.167],"y":[-0.024,-0.024,0]},"t":165,"s":[119.607,119.607,100]},{"t":195,"s":[0,0,100]}],"ix":6,"l":2}},"ao":0,"shapes":[{"ty":"gr","it":[{"ind":0,"ty":"sh","ix":1,"ks":{"a":0,"k":{"i":[[0,10.369],[8.743,4.24],[0,0]],"o":[[0,-10.369],[0,0],[8.743,-4.24]],"v":[[7.386,0],[-7.386,-23.57],[-7.386,23.57]],"c":true},"ix":2},"nm":"Path 1","mn":"ADBE Vector Shape - Group","hd":false},{"ty":"fl","c":{"a":0,"k":[0.40000000596,0.615686297417,0.964705884457,1],"ix":4},"o":{"a":0,"k":100,"ix":5},"r":1,"bm":0,"nm":"Fill 1","mn":"ADBE Vector Graphic - Fill","hd":false},{"ty":"tr","p":{"a":0,"k":[0,0],"ix":2},"a":{"a":0,"k":[0,0],"ix":1},"s":{"a":0,"k":[100,100],"ix":3},"r":{"a":0,"k":0,"ix":6},"o":{"a":0,"k":100,"ix":7},"sk":{"a":0,"k":0,"ix":4},"sa":{"a":0,"k":0,"ix":5},"nm":"Transform"}],"nm":"Group 1","np":2,"cix":2,"bm":0,"ix":1,"mn":"ADBE Vector Group","hd":false}],"ip":0,"op":360,"st":0,"bm":0},{"ddd":0,"ind":16,"ty":4,"nm":"Squeeze Gesture","sr":1,"ks":{"o":{"a":1,"k":[{"i":{"x":[0.833],"y":[0.833]},"o":{"x":[0.167],"y":[0.167]},"t":121,"s":[0]},{"i":{"x":[0.833],"y":[0.833]},"o":{"x":[0.167],"y":[0.167]},"t":149,"s":[50]},{"i":{"x":[0.833],"y":[0.833]},"o":{"x":[0.167],"y":[0.167]},"t":165,"s":[50]},{"t":195,"s":[0]}],"ix":11},"r":{"a":0,"k":0,"ix":10},"p":{"a":0,"k":[147.576,163.908,0],"ix":2,"l":2},"a":{"a":0,"k":[-12.125,0,0],"ix":1,"l":2},"s":{"a":1,"k":[{"i":{"x":[0.775,0.775,0.833],"y":[0.949,0.949,1]},"o":{"x":[0.4,0.4,0.4],"y":[0,0,0]},"t":121,"s":[45,45,100]},{"i":{"x":[0.759,0.759,0.833],"y":[0.856,0.856,1]},"o":{"x":[0.398,0.398,0.167],"y":[0.467,0.467,0]},"t":157,"s":[114.737,114.737,100]},{"i":{"x":[0.667,0.667,0.667],"y":[1,1,1]},"o":{"x":[0.393,0.393,0.167],"y":[-0.022,-0.022,0]},"t":165,"s":[117.737,117.737,100]},{"t":195,"s":[0,0,100]}],"ix":6,"l":2}},"ao":0,"shapes":[{"ty":"gr","it":[{"ind":0,"ty":"sh","ix":1,"ks":{"a":0,"k":{"i":[[14.068,4.758],[0,0],[0,0],[0,0],[0,15.674]],"o":[[0,0],[0,0],[0,0],[14.068,-4.758],[0,-15.674]],"v":[[-12.099,-33.73],[-12.099,-23.57],[-12.099,23.57],[-12.099,33.73],[12.099,0]],"c":true},"ix":2},"nm":"Path 1","mn":"ADBE Vector Shape - Group","hd":false},{"ty":"fl","c":{"a":0,"k":[0.40000000596,0.615686297417,0.964705884457,1],"ix":4},"o":{"a":0,"k":100,"ix":5},"r":1,"bm":0,"nm":"Fill 1","mn":"ADBE Vector Graphic - Fill","hd":false},{"ty":"tr","p":{"a":0,"k":[0,0],"ix":2},"a":{"a":0,"k":[0,0],"ix":1},"s":{"a":0,"k":[100,100],"ix":3},"r":{"a":0,"k":0,"ix":6},"o":{"a":0,"k":100,"ix":7},"sk":{"a":0,"k":0,"ix":4},"sa":{"a":0,"k":0,"ix":5},"nm":"Transform"}],"nm":"Group 1","np":2,"cix":2,"bm":0,"ix":1,"mn":"ADBE Vector Group","hd":false}],"ip":0,"op":360,"st":0,"bm":0},{"ddd":0,"ind":17,"ty":4,"nm":".grey600","cl":"grey600","sr":1,"ks":{"o":{"a":0,"k":100,"ix":11},"r":{"a":0,"k":0,"ix":10},"p":{"a":0,"k":[204,150,0],"ix":2,"l":2},"a":{"a":0,"k":[0,0,0],"ix":1,"l":2},"s":{"a":0,"k":[100,100,100],"ix":6,"l":2}},"ao":0,"shapes":[{"ty":"gr","it":[{"ind":0,"ty":"sh","ix":1,"ks":{"a":0,"k":{"i":[[0,0],[4.626,0],[0,0],[0,4.626],[0,0],[-4.626,0],[0,0],[0,-4.626]],"o":[[0,4.626],[0,0],[-4.626,0],[0,0],[0,-4.626],[0,0],[4.626,0],[0,0]],"v":[[56.866,88.829],[48.477,97.22],[-48.009,97.22],[-56.398,88.829],[-56.398,-112.53],[-48.009,-120.92],[48.477,-120.92],[56.866,-112.53]],"c":true},"ix":2},"nm":"Path 1","mn":"ADBE Vector Shape - Group","hd":false},{"ind":1,"ty":"sh","ix":2,"ks":{"a":0,"k":{"i":[[0,1.158],[0,0],[1.158,0],[0,0],[5.783,0],[0,0],[0,-5.783],[0,0],[-5.783,0],[0,0],[0,5.783],[0,0],[0,1.158],[0,0],[1.158,0],[0,0]],"o":[[0,0],[0,-1.158],[0,0],[0,-5.783],[0,0],[-5.783,0],[0,0],[0,5.783],[0,0],[5.783,0],[0,0],[1.158,0],[0,0],[0,-1.158],[0,0],[1.158,0]],"v":[[61.061,-57.995],[61.061,-66.385],[58.964,-68.483],[58.964,-112.53],[48.477,-123.018],[-48.009,-123.018],[-58.496,-112.53],[-58.496,88.829],[-48.009,99.318],[48.477,99.318],[58.964,88.829],[58.964,-13.948],[61.061,-16.045],[61.061,-37.02],[58.964,-39.118],[58.964,-55.898]],"c":true},"ix":2},"nm":"Path 2","mn":"ADBE Vector Shape - Group","hd":false},{"ty":"fl","c":{"a":0,"k":[0.501960813999,0.525490224361,0.54509806633,1],"ix":4},"o":{"a":0,"k":100,"ix":5},"r":1,"bm":0,"nm":"Fill 1","mn":"ADBE Vector Graphic - Fill","hd":false},{"ty":"tr","p":{"a":0,"k":[0,0],"ix":2},"a":{"a":0,"k":[0,0],"ix":1},"s":{"a":0,"k":[100,100],"ix":3},"r":{"a":0,"k":0,"ix":6},"o":{"a":0,"k":100,"ix":7},"sk":{"a":0,"k":0,"ix":4},"sa":{"a":0,"k":0,"ix":5},"nm":"Transform"}],"nm":"Group 1","np":3,"cix":2,"bm":0,"ix":1,"mn":"ADBE Vector Group","hd":false}],"ip":0,"op":360,"st":0,"bm":0},{"ddd":0,"ind":18,"ty":4,"nm":".black","cl":"black","sr":1,"ks":{"o":{"a":0,"k":100,"ix":11},"r":{"a":0,"k":0,"ix":10},"p":{"a":0,"k":[204.234,138.15,0],"ix":2,"l":2},"a":{"a":0,"k":[0,0,0],"ix":1,"l":2},"s":{"a":0,"k":[100,100,100],"ix":6,"l":2}},"ao":0,"shapes":[{"ty":"gr","it":[{"ind":0,"ty":"sh","ix":1,"ks":{"a":0,"k":{"i":[[0,0],[4.626,0],[0,0],[0,4.626],[0,0],[-4.626,0],[0,0],[0,-4.626]],"o":[[0,4.626],[0,0],[-4.626,0],[0,0],[0,-4.626],[0,0],[4.626,0],[0,0]],"v":[[56.632,100.68],[48.243,109.07],[-48.243,109.07],[-56.632,100.68],[-56.632,-100.68],[-48.243,-109.07],[48.243,-109.07],[56.632,-100.68]],"c":true},"ix":2},"nm":"Path 1","mn":"ADBE Vector Shape - Group","hd":false},{"ty":"fl","c":{"a":0,"k":[0,0,0,1],"ix":4},"o":{"a":0,"k":100,"ix":5},"r":1,"bm":0,"nm":"Fill 1","mn":"ADBE Vector Graphic - Fill","hd":false},{"ty":"tr","p":{"a":0,"k":[0,0],"ix":2},"a":{"a":0,"k":[0,0],"ix":1},"s":{"a":0,"k":[100,100],"ix":3},"r":{"a":0,"k":0,"ix":6},"o":{"a":0,"k":100,"ix":7},"sk":{"a":0,"k":0,"ix":4},"sa":{"a":0,"k":0,"ix":5},"nm":"Transform"}],"nm":"Group 1","np":2,"cix":2,"bm":0,"ix":1,"mn":"ADBE Vector Group","hd":false}],"ip":0,"op":360,"st":0,"bm":0},{"ddd":0,"ind":19,"ty":4,"nm":"Hand Back 2","sr":1,"ks":{"o":{"a":0,"k":100,"ix":11},"r":{"a":0,"k":0,"ix":10},"p":{"a":0,"k":[237.658,209.243,0],"ix":2,"l":2},"a":{"a":0,"k":[0,0,0],"ix":1,"l":2},"s":{"a":0,"k":[100,100,100],"ix":6,"l":2}},"ao":0,"shapes":[{"ty":"gr","it":[{"ind":0,"ty":"sh","ix":1,"ks":{"a":0,"k":{"i":[[0,32.889],[5.494,9.152],[0,0],[0,0],[0,0],[2.488,-4.35],[0,0],[0,0],[0.002,-0.004],[0,0],[0,0],[1.154,-3.176],[0,0],[-51.516,-0.098],[-0.675,0.036]],"o":[[0,-11.461],[0,0],[-14.944,-29.419],[0,0],[-3.443,3.589],[0,0],[0,0],[-0.002,0.004],[-0.005,-0.004],[0,0],[-1.642,2.904],[0,0],[0,0],[0.739,0.001],[32.522,-1.121]],"v":[[68.313,14.532],[59.655,-16.799],[59.659,-16.799],[-0.359,-75.372],[-36.06,-27.634],[-44.996,-15.685],[-45.073,-15.583],[-45.055,-15.583],[-45.061,-15.573],[-45.073,-15.583],[-45.147,-15.423],[-49.365,-6.298],[-68.313,34.693],[7.649,75.372],[9.765,75.318]],"c":true},"ix":2},"nm":"Path 1","mn":"ADBE Vector Shape - Group","hd":false},{"ty":"fl","c":{"a":0,"k":[0.678431391716,0.403921574354,0.305882364511,1],"ix":4},"o":{"a":0,"k":100,"ix":5},"r":1,"bm":0,"nm":"Fill 1","mn":"ADBE Vector Graphic - Fill","hd":false},{"ty":"tr","p":{"a":0,"k":[0,0],"ix":2},"a":{"a":0,"k":[0,0],"ix":1},"s":{"a":0,"k":[100,100],"ix":3},"r":{"a":0,"k":0,"ix":6},"o":{"a":0,"k":100,"ix":7},"sk":{"a":0,"k":0,"ix":4},"sa":{"a":0,"k":0,"ix":5},"nm":"Transform"}],"nm":"Group 1","np":2,"cix":2,"bm":0,"ix":1,"mn":"ADBE Vector Group","hd":false}],"ip":0,"op":360,"st":0,"bm":0},{"ddd":0,"ind":20,"ty":4,"nm":"Hand Back","sr":1,"ks":{"o":{"a":0,"k":100,"ix":11},"r":{"a":0,"k":0,"ix":10},"p":{"a":0,"k":[175.395,133.871,0],"ix":2,"l":2},"a":{"a":0,"k":[0,0,0],"ix":1,"l":2},"s":{"a":0,"k":[100,100,100],"ix":6,"l":2}},"ao":0,"shapes":[{"ty":"gr","it":[{"ind":0,"ty":"sh","ix":1,"ks":{"a":1,"k":[{"i":{"x":0.7,"y":1},"o":{"x":0.5,"y":0},"t":120,"s":[{"i":[[-4.032,-4.347],[0,0],[0,0],[0,0],[3.706,-4.95],[0,0]],"o":[[0,0],[0,0],[0,0],[-5.375,-3.056],[0,0],[-3.553,4.746]],"v":[[-48.572,-28.717],[21.058,49.336],[51.846,0.801],[-33.508,-47.731],[-49.398,-44.417],[-49.398,-44.417]],"c":true}]},{"i":{"x":0.52,"y":1},"o":{"x":0.28,"y":0},"t":139,"s":[{"i":[[-3.754,-4.589],[0,0],[0,0],[0,0],[4.006,-4.71],[0,0]],"o":[[0,0],[0,0],[0,0],[-5.175,-3.384],[0,0],[-3.841,4.516]],"v":[[-47.085,-30.827],[21.058,49.336],[51.846,0.801],[-30.869,-48.869],[-46.934,-46.549],[-46.934,-46.549]],"c":true}]},{"i":{"x":0.48,"y":1},"o":{"x":0.46,"y":0},"t":165,"s":[{"i":[[-3.528,-4.765],[0,0],[0,0],[0,0],[4.228,-4.511],[0,0]],"o":[[0,0],[0,0],[0,0],[-5.006,-3.63],[0,0],[-4.055,4.326]],"v":[[-46.045,-32.053],[21.058,49.336],[51.846,0.801],[-28.978,-49.292],[-45.137,-47.749],[-45.137,-47.749]],"c":true}]},{"t":185,"s":[{"i":[[-4.032,-4.347],[0,0],[0,0],[0,0],[3.706,-4.95],[0,0]],"o":[[0,0],[0,0],[0,0],[-5.375,-3.056],[0,0],[-3.553,4.746]],"v":[[-48.572,-28.717],[21.058,49.336],[51.846,0.801],[-33.508,-47.731],[-49.398,-44.417],[-49.398,-44.417]],"c":true}]}],"ix":2},"nm":"Path 1","mn":"ADBE Vector Shape - Group","hd":false},{"ty":"fl","c":{"a":0,"k":[0.678431391716,0.403921574354,0.305882364511,1],"ix":4},"o":{"a":0,"k":100,"ix":5},"r":1,"bm":0,"nm":"Fill 1","mn":"ADBE Vector Graphic - Fill","hd":false},{"ty":"tr","p":{"a":0,"k":[0,0],"ix":2},"a":{"a":0,"k":[0,0],"ix":1},"s":{"a":0,"k":[100,100],"ix":3},"r":{"a":0,"k":0,"ix":6},"o":{"a":0,"k":100,"ix":7},"sk":{"a":0,"k":0,"ix":4},"sa":{"a":0,"k":0,"ix":5},"nm":"Transform"}],"nm":"Group 1","np":2,"cix":2,"bm":0,"ix":1,"mn":"ADBE Vector Group","hd":false}],"ip":0,"op":360,"st":0,"bm":0}],"markers":[]}